{
  "$schema": "https://mintlify.com/docs.json",
  "theme": "mint",
  "name": "ContentHero",
  "description": "The context and execution layer for AI content creation. Generate media, ground posts in your brand voice, and publish, all driven by your own agent.",
  "colors": {
    "primary": "#d4af37",
    "light": "#e0c25a",
    "dark": "#b89a30"
  },
  "favicon": "/favicon.svg",
  "navigation": {
    "tabs": [
      {
        "tab": "Documentation",
        "groups": [
          {
            "group": "Get Started",
            "pages": [
              "index",
              "for-ai-agents",
              "quickstart"
            ]
          },
          {
            "group": "Authentication",
            "pages": [
              "authentication/api-keys",
              "authentication/oauth"
            ]
          },
          {
            "group": "Account",
            "pages": [
              "account-billing"
            ]
          },
          {
            "group": "Guides",
            "pages": [
              "guides/generate",
              "guides/pipeline",
              "guides/brand",
              "guides/inspiration"
            ]
          },
          {
            "group": "Tools",
            "pages": [
              "tools/mcp",
              "tools/cli"
            ]
          },
          {
            "group": "Recipes",
            "pages": [
              "cookbook"
            ]
          }
        ]
      },
      {
        "tab": "API Reference",
        "groups": [
          {
            "group": "API Reference",
            "pages": [
              "api-reference/overview"
            ]
          }
        ]
      }
    ]
  },
  "logo": {
    "light": "/logo/light.svg",
    "dark": "/logo/dark.svg"
  },
  "navbar": {
    "links": [
      {
        "label": "App",
        "href": "https://app.contenthero.ai"
      },
      {
        "label": "Skills",
        "href": "https://github.com/contenthero-ai/skills"
      }
    ],
    "primary": {
      "type": "button",
      "label": "Get an API key",
      "href": "https://app.contenthero.ai"
    }
  },
  "footer": {
    "socials": {
      "github": "https://github.com/contenthero-ai"
    }
  }
}
